{
  "timestamp": 1770602290,
  "date": "20260209_025810",
  "cause": "Unknown",
  "reward": -10,
  "snake": {
    "x": 34932.46551396976,
    "y": 34534.55870463508,
    "len": 24,
    "ang": 5.8659425328746915
  },
  "env": {
    "dist_to_wall": -8929.297567188814,
    "map_radius": 21600,
    "view_radius": 388.89128954842715,
    "boundary_type": "circle"
  },
  "debug": {
    "boundary_source": "pbx",
    "boundary_type": "polygon",
    "dist_from_center": 0,
    "dist_to_wall": -8929,
    "map_vars": {
      "FINAL_dist_to_wall": -8929,
      "FINAL_source": "pbx",
      "dist_from_center": 0,
      "map_center": "21600,21600",
      "map_radius": 21600,
      "pbx_count": 32767
    },
    "snake_x": 34932,
    "snake_y": 34535,
    "total_foods": 162,
    "total_slithers": 1,
    "visible_enemies": 0,
    "visible_foods": 13
  }
}