{
  "timestamp": 1770540414,
  "date": "20260208_094654",
  "cause": "Wall",
  "reward": -100,
  "snake": {
    "x": 29628.692997381568,
    "y": 38042.04231905862,
    "len": 27,
    "ang": 0.8747003745041526
  },
  "env": {
    "dist_to_wall": -14687.670295078206,
    "map_radius": 21600,
    "view_radius": 388.89128954842715,
    "boundary_type": "polygon"
  },
  "debug": {
    "boundary_source": "pbx",
    "boundary_type": "polygon",
    "dist_from_center": 0,
    "dist_to_wall": -14688,
    "map_vars": {
      "FINAL_dist_to_wall": -14688,
      "FINAL_source": "pbx",
      "dist_from_center": 0,
      "map_center": "21600,21600",
      "map_radius": 21600,
      "pbx_count": 32767
    },
    "snake_x": 29629,
    "snake_y": 38042,
    "total_foods": 656,
    "total_slithers": 7,
    "visible_enemies": 5,
    "visible_foods": 27
  }
}