{
  "timestamp": 1770582224,
  "date": "20260208_212344",
  "cause": "SnakeCollision",
  "reward": -10,
  "snake": {
    "x": 37174.02897851555,
    "y": 30973.753917500726,
    "len": 26,
    "ang": 0.22089323345553233
  },
  "env": {
    "dist_to_wall": -12004.365863472529,
    "map_radius": 21600,
    "view_radius": 388.89128954842715,
    "boundary_type": "circle"
  },
  "debug": {
    "boundary_source": "pbx",
    "boundary_type": "polygon",
    "dist_from_center": 0,
    "dist_to_wall": -12004,
    "map_vars": {
      "FINAL_dist_to_wall": -12004,
      "FINAL_source": "pbx",
      "dist_from_center": 0,
      "map_center": "21600,21600",
      "map_radius": 21600,
      "pbx_count": 32767
    },
    "snake_x": 37174,
    "snake_y": 30974,
    "total_foods": 636,
    "total_slithers": 7,
    "visible_enemies": 6,
    "visible_foods": 46
  }
}