{
  "timestamp": 1770650231,
  "date": "20260209_161711",
  "cause": "SnakeCollision",
  "reward": -10,
  "snake": {
    "x": 35688.73605194126,
    "y": 37258.513614626405,
    "len": 25,
    "ang": 0
  },
  "env": {
    "dist_to_wall": -7412.725526343861,
    "map_radius": 21600,
    "view_radius": 388.89128954842715,
    "boundary_type": "circle"
  },
  "debug": {
    "boundary_source": "pbx",
    "boundary_type": "polygon",
    "dist_from_center": 0,
    "dist_to_wall": -7413,
    "map_vars": {
      "FINAL_dist_to_wall": -7413,
      "FINAL_source": "pbx",
      "dist_from_center": 0,
      "map_center": "21600,21600",
      "map_radius": 21600,
      "pbx_count": 32767
    },
    "snake_x": 35689,
    "snake_y": 37259,
    "total_foods": 646,
    "total_slithers": 5,
    "visible_enemies": 4,
    "visible_foods": 58
  }
}