{
  "timestamp": 1770569040,
  "date": "20260208_174400",
  "cause": "SnakeCollision",
  "reward": -10,
  "snake": {
    "x": 37324.949116573116,
    "y": 25674.90285902576,
    "len": 32,
    "ang": 0.2699806186678728
  },
  "env": {
    "dist_to_wall": -15058.266234262142,
    "map_radius": 21600,
    "view_radius": 388.89128954842715,
    "boundary_type": "circle"
  },
  "debug": {
    "boundary_source": "pbx",
    "boundary_type": "polygon",
    "dist_from_center": 0,
    "dist_to_wall": -15058,
    "map_vars": {
      "FINAL_dist_to_wall": -15058,
      "FINAL_source": "pbx",
      "dist_from_center": 0,
      "map_center": "21600,21600",
      "map_radius": 21600,
      "pbx_count": 32767
    },
    "snake_x": 37325,
    "snake_y": 25675,
    "total_foods": 586,
    "total_slithers": 4,
    "visible_enemies": 3,
    "visible_foods": 50
  }
}