{
  "timestamp": 1770621035,
  "date": "20260209_081035",
  "cause": "Wall",
  "reward": -50,
  "snake": {
    "x": 40588.67843195265,
    "y": 38133.29392080737,
    "len": 26,
    "ang": 0.2699806186678728
  },
  "env": {
    "dist_to_wall": -11676.119769689074,
    "map_radius": 21600,
    "view_radius": 388.89128954842715,
    "boundary_type": "circle"
  },
  "debug": {
    "boundary_source": "pbx",
    "boundary_type": "polygon",
    "dist_from_center": 0,
    "dist_to_wall": -11676,
    "map_vars": {
      "FINAL_dist_to_wall": -11676,
      "FINAL_source": "pbx",
      "dist_from_center": 0,
      "map_center": "21600,21600",
      "map_radius": 21600,
      "pbx_count": 32767
    },
    "snake_x": 40589,
    "snake_y": 38133,
    "total_foods": 334,
    "total_slithers": 1,
    "visible_enemies": 0,
    "visible_foods": 2
  }
}