{
  "timestamp": 1770550023,
  "date": "20260208_122703",
  "cause": "Wall",
  "reward": -100,
  "snake": {
    "x": 40277.82000658137,
    "y": 40867.128841649246,
    "len": 25,
    "ang": 5.890486225480862
  },
  "env": {
    "dist_to_wall": -5102.498545902158,
    "map_radius": 21600,
    "view_radius": 388.89128954842715,
    "boundary_type": "circle"
  },
  "debug": {
    "boundary_source": "pbx",
    "boundary_type": "polygon",
    "dist_from_center": 0,
    "dist_to_wall": -5102,
    "map_vars": {
      "FINAL_dist_to_wall": -5102,
      "FINAL_source": "pbx",
      "dist_from_center": 0,
      "map_center": "21600,21600",
      "map_radius": 21600,
      "pbx_count": 32767
    },
    "snake_x": 40278,
    "snake_y": 40867,
    "total_foods": 422,
    "total_slithers": 1,
    "visible_enemies": 0,
    "visible_foods": 48
  }
}