{
  "timestamp": 1770539745,
  "date": "20260208_093545",
  "cause": "Wall",
  "reward": -100,
  "snake": {
    "x": 31628.81777771301,
    "y": 32167.374844897808,
    "len": 25,
    "ang": 0.04908738521234052
  },
  "env": {
    "dist_to_wall": -1786.114960363135,
    "map_radius": 21600,
    "view_radius": 388.89128954842715,
    "boundary_type": "polygon"
  },
  "debug": {
    "boundary_source": "pbx",
    "boundary_type": "polygon",
    "dist_from_center": 0,
    "dist_to_wall": -1786,
    "map_vars": {
      "FINAL_dist_to_wall": -1786,
      "FINAL_source": "pbx",
      "dist_from_center": 0,
      "map_center": "21600,21600",
      "map_radius": 21600,
      "pbx_count": 32767
    },
    "snake_x": 31629,
    "snake_y": 32167,
    "total_foods": 631,
    "total_slithers": 10,
    "visible_enemies": 9,
    "visible_foods": 46
  }
}