{
  "timestamp": 1770626908,
  "date": "20260209_094828",
  "cause": "SnakeCollision",
  "reward": -10,
  "snake": {
    "x": 30727.03451102756,
    "y": 35622.78307106976,
    "len": 20,
    "ang": 0.44178646691106466
  },
  "env": {
    "dist_to_wall": -4049.753198912596,
    "map_radius": 21600,
    "view_radius": 388.89128954842715,
    "boundary_type": "circle"
  },
  "debug": {
    "boundary_source": "pbx",
    "boundary_type": "polygon",
    "dist_from_center": 0,
    "dist_to_wall": -4050,
    "map_vars": {
      "FINAL_dist_to_wall": -4050,
      "FINAL_source": "pbx",
      "dist_from_center": 0,
      "map_center": "21600,21600",
      "map_radius": 21600,
      "pbx_count": 32767
    },
    "snake_x": 30727,
    "snake_y": 35623,
    "total_foods": 549,
    "total_slithers": 4,
    "visible_enemies": 3,
    "visible_foods": 45
  }
}