{
  "timestamp": 1770592580,
  "date": "20260209_001620",
  "cause": "SnakeCollision",
  "reward": -10,
  "snake": {
    "x": 39797.50977517661,
    "y": 28245.273601333116,
    "len": 30,
    "ang": 6.037748381117884
  },
  "env": {
    "dist_to_wall": -6171.667880241381,
    "map_radius": 21600,
    "view_radius": 388.89128954842715,
    "boundary_type": "circle"
  },
  "debug": {
    "boundary_source": "pbx",
    "boundary_type": "polygon",
    "dist_from_center": 0,
    "dist_to_wall": -6172,
    "map_vars": {
      "FINAL_dist_to_wall": -6172,
      "FINAL_source": "pbx",
      "dist_from_center": 0,
      "map_center": "21600,21600",
      "map_radius": 21600,
      "pbx_count": 32767
    },
    "snake_x": 39798,
    "snake_y": 28245,
    "total_foods": 398,
    "total_slithers": 3,
    "visible_enemies": 2,
    "visible_foods": 5
  }
}