{
  "timestamp": 1770597706,
  "date": "20260209_014146",
  "cause": "SnakeCollision",
  "reward": -10,
  "snake": {
    "x": 35872.92561744185,
    "y": 36539.711496315875,
    "len": 25,
    "ang": 0.859029241215959
  },
  "env": {
    "dist_to_wall": -2534.9456051037164,
    "map_radius": 21600,
    "view_radius": 388.89128954842715,
    "boundary_type": "circle"
  },
  "debug": {
    "boundary_source": "pbx",
    "boundary_type": "polygon",
    "dist_from_center": 0,
    "dist_to_wall": -2535,
    "map_vars": {
      "FINAL_dist_to_wall": -2535,
      "FINAL_source": "pbx",
      "dist_from_center": 0,
      "map_center": "21600,21600",
      "map_radius": 21600,
      "pbx_count": 32767
    },
    "snake_x": 35873,
    "snake_y": 36540,
    "total_foods": 616,
    "total_slithers": 6,
    "visible_enemies": 5,
    "visible_foods": 33
  }
}