{
  "timestamp": 1770568523,
  "date": "20260208_173523",
  "cause": "Wall",
  "reward": -50,
  "snake": {
    "x": 38962.26899709276,
    "y": 40559.31098307729,
    "len": 25,
    "ang": 0
  },
  "env": {
    "dist_to_wall": -14967.941814596727,
    "map_radius": 21600,
    "view_radius": 388.89128954842715,
    "boundary_type": "circle"
  },
  "debug": {
    "boundary_source": "pbx",
    "boundary_type": "polygon",
    "dist_from_center": 0,
    "dist_to_wall": -14968,
    "map_vars": {
      "FINAL_dist_to_wall": -14968,
      "FINAL_source": "pbx",
      "dist_from_center": 0,
      "map_center": "21600,21600",
      "map_radius": 21600,
      "pbx_count": 32767
    },
    "snake_x": 38962,
    "snake_y": 40559,
    "total_foods": 384,
    "total_slithers": 5,
    "visible_enemies": 4,
    "visible_foods": 15
  }
}