{
  "timestamp": 1770592616,
  "date": "20260209_001656",
  "cause": "SnakeCollision",
  "reward": -10,
  "snake": {
    "x": 32521.214804417377,
    "y": 36435.92581278329,
    "len": 26,
    "ang": 5.890486225480862
  },
  "env": {
    "dist_to_wall": -4716.575686783374,
    "map_radius": 21600,
    "view_radius": 388.89128954842715,
    "boundary_type": "circle"
  },
  "debug": {
    "boundary_source": "pbx",
    "boundary_type": "polygon",
    "dist_from_center": 0,
    "dist_to_wall": -4717,
    "map_vars": {
      "FINAL_dist_to_wall": -4717,
      "FINAL_source": "pbx",
      "dist_from_center": 0,
      "map_center": "21600,21600",
      "map_radius": 21600,
      "pbx_count": 32767
    },
    "snake_x": 32521,
    "snake_y": 36436,
    "total_foods": 473,
    "total_slithers": 7,
    "visible_enemies": 6,
    "visible_foods": 30
  }
}