{
  "timestamp": 1770567133,
  "date": "20260208_171213",
  "cause": "SnakeCollision",
  "reward": -10,
  "snake": {
    "x": 38979.89673176251,
    "y": 27220.600790456403,
    "len": 26,
    "ang": 0.8835729338221293
  },
  "env": {
    "dist_to_wall": -15636.433538583382,
    "map_radius": 21600,
    "view_radius": 388.89128954842715,
    "boundary_type": "circle"
  },
  "debug": {
    "boundary_source": "pbx",
    "boundary_type": "polygon",
    "dist_from_center": 0,
    "dist_to_wall": -15636,
    "map_vars": {
      "FINAL_dist_to_wall": -15636,
      "FINAL_source": "pbx",
      "dist_from_center": 0,
      "map_center": "21600,21600",
      "map_radius": 21600,
      "pbx_count": 32767
    },
    "snake_x": 38980,
    "snake_y": 27221,
    "total_foods": 664,
    "total_slithers": 5,
    "visible_enemies": 4,
    "visible_foods": 78
  }
}