{
  "timestamp": 1770567246,
  "date": "20260208_171406",
  "cause": "SnakeCollision",
  "reward": -10,
  "snake": {
    "x": 37979.40945141399,
    "y": 24615.456963309112,
    "len": 45,
    "ang": 6.135923151542564
  },
  "env": {
    "dist_to_wall": -16210.980663672568,
    "map_radius": 21600,
    "view_radius": 402.65744087512627,
    "boundary_type": "circle"
  },
  "debug": {
    "boundary_source": "pbx",
    "boundary_type": "polygon",
    "dist_from_center": 0,
    "dist_to_wall": -16211,
    "map_vars": {
      "FINAL_dist_to_wall": -16211,
      "FINAL_source": "pbx",
      "dist_from_center": 0,
      "map_center": "21600,21600",
      "map_radius": 21600,
      "pbx_count": 32767
    },
    "snake_x": 37979,
    "snake_y": 24615,
    "total_foods": 538,
    "total_slithers": 3,
    "visible_enemies": 2,
    "visible_foods": 47
  }
}