{
  "timestamp": 1770639094,
  "date": "20260209_131134",
  "cause": "SnakeCollision",
  "reward": -10,
  "snake": {
    "x": 31565.931504883647,
    "y": 28037.387006242818,
    "len": 25,
    "ang": 0.3190680038802134
  },
  "env": {
    "dist_to_wall": -5508.375726415777,
    "map_radius": 21600,
    "view_radius": 388.89128954842715,
    "boundary_type": "circle"
  },
  "debug": {
    "boundary_source": "pbx",
    "boundary_type": "polygon",
    "dist_from_center": 0,
    "dist_to_wall": -5508,
    "map_vars": {
      "FINAL_dist_to_wall": -5508,
      "FINAL_source": "pbx",
      "dist_from_center": 0,
      "map_center": "21600,21600",
      "map_radius": 21600,
      "pbx_count": 32767
    },
    "snake_x": 31566,
    "snake_y": 28037,
    "total_foods": 637,
    "total_slithers": 6,
    "visible_enemies": 5,
    "visible_foods": 73
  }
}