{
  "timestamp": 1770574007,
  "date": "20260208_190647",
  "cause": "SnakeCollision",
  "reward": -10,
  "snake": {
    "x": 34998.56351143333,
    "y": 34790.531265343976,
    "len": 25,
    "ang": 0.9326603190344698
  },
  "env": {
    "dist_to_wall": -10136.280043043287,
    "map_radius": 21600,
    "view_radius": 388.89128954842715,
    "boundary_type": "circle"
  },
  "debug": {
    "boundary_source": "pbx",
    "boundary_type": "polygon",
    "dist_from_center": 0,
    "dist_to_wall": -10136,
    "map_vars": {
      "FINAL_dist_to_wall": -10136,
      "FINAL_source": "pbx",
      "dist_from_center": 0,
      "map_center": "21600,21600",
      "map_radius": 21600,
      "pbx_count": 32767
    },
    "snake_x": 34999,
    "snake_y": 34791,
    "total_foods": 675,
    "total_slithers": 10,
    "visible_enemies": 9,
    "visible_foods": 104
  }
}