{
  "timestamp": 1770592204,
  "date": "20260209_001004",
  "cause": "SnakeCollision",
  "reward": -10,
  "snake": {
    "x": 30840.091773815995,
    "y": 32177.603780922862,
    "len": 28,
    "ang": 0
  },
  "env": {
    "dist_to_wall": -4208.580727720861,
    "map_radius": 21600,
    "view_radius": 388.89128954842715,
    "boundary_type": "circle"
  },
  "debug": {
    "boundary_source": "pbx",
    "boundary_type": "polygon",
    "dist_from_center": 0,
    "dist_to_wall": -4209,
    "map_vars": {
      "FINAL_dist_to_wall": -4209,
      "FINAL_source": "pbx",
      "dist_from_center": 0,
      "map_center": "21600,21600",
      "map_radius": 21600,
      "pbx_count": 32767
    },
    "snake_x": 30840,
    "snake_y": 32178,
    "total_foods": 721,
    "total_slithers": 19,
    "visible_enemies": 17,
    "visible_foods": 39
  }
}