{
  "timestamp": 1770583340,
  "date": "20260208_214220",
  "cause": "Wall",
  "reward": -50,
  "snake": {
    "x": 41450.35487101964,
    "y": 34715.05658413937,
    "len": 25,
    "ang": 0.7707557334432389
  },
  "env": {
    "dist_to_wall": -2647.7548459873556,
    "map_radius": 21600,
    "view_radius": 388.89128954842715,
    "boundary_type": "circle"
  },
  "debug": {
    "boundary_source": "pbx",
    "boundary_type": "polygon",
    "dist_from_center": 0,
    "dist_to_wall": -2648,
    "map_vars": {
      "FINAL_dist_to_wall": -2648,
      "FINAL_source": "pbx",
      "dist_from_center": 0,
      "map_center": "21600,21600",
      "map_radius": 21600,
      "pbx_count": 32767
    },
    "snake_x": 41450,
    "snake_y": 34715,
    "total_foods": 498,
    "total_slithers": 5,
    "visible_enemies": 4,
    "visible_foods": 40
  }
}