{
  "timestamp": 1770602609,
  "date": "20260209_030329",
  "cause": "SnakeCollision",
  "reward": -10,
  "snake": {
    "x": 27394.868482529808,
    "y": 34320.236353228225,
    "len": 24,
    "ang": 0.3436116964863836
  },
  "env": {
    "dist_to_wall": -3708.5284849230256,
    "map_radius": 21600,
    "view_radius": 388.89128954842715,
    "boundary_type": "circle"
  },
  "debug": {
    "boundary_source": "pbx",
    "boundary_type": "polygon",
    "dist_from_center": 0,
    "dist_to_wall": -3709,
    "map_vars": {
      "FINAL_dist_to_wall": -3709,
      "FINAL_source": "pbx",
      "dist_from_center": 0,
      "map_center": "21600,21600",
      "map_radius": 21600,
      "pbx_count": 32767
    },
    "snake_x": 27395,
    "snake_y": 34320,
    "total_foods": 338,
    "total_slithers": 5,
    "visible_enemies": 4,
    "visible_foods": 16
  }
}