{
  "timestamp": 1770567266,
  "date": "20260208_171426",
  "cause": "SnakeCollision",
  "reward": -10,
  "snake": {
    "x": 33710.40220394858,
    "y": 29467.594459794516,
    "len": 26,
    "ang": 0
  },
  "env": {
    "dist_to_wall": -3675.3296871714733,
    "map_radius": 21600,
    "view_radius": 388.89128954842715,
    "boundary_type": "circle"
  },
  "debug": {
    "boundary_source": "pbx",
    "boundary_type": "polygon",
    "dist_from_center": 0,
    "dist_to_wall": -3675,
    "map_vars": {
      "FINAL_dist_to_wall": -3675,
      "FINAL_source": "pbx",
      "dist_from_center": 0,
      "map_center": "21600,21600",
      "map_radius": 21600,
      "pbx_count": 32767
    },
    "snake_x": 33710,
    "snake_y": 29468,
    "total_foods": 676,
    "total_slithers": 14,
    "visible_enemies": 13,
    "visible_foods": 55
  }
}