{
  "timestamp": 1770558476,
  "date": "20260208_144756",
  "cause": "Wall",
  "reward": -100,
  "snake": {
    "x": 42391.80204056072,
    "y": 41386.799843727546,
    "len": 31,
    "ang": 0.201938413139112
  },
  "env": {
    "dist_to_wall": -18889.333727366517,
    "map_radius": 21600,
    "view_radius": 388.89128954842715,
    "boundary_type": "circle"
  },
  "debug": {
    "boundary_source": "pbx",
    "boundary_type": "polygon",
    "dist_from_center": 0,
    "dist_to_wall": -18889,
    "map_vars": {
      "FINAL_dist_to_wall": -18889,
      "FINAL_source": "pbx",
      "dist_from_center": 0,
      "map_center": "21600,21600",
      "map_radius": 21600,
      "pbx_count": 32767
    },
    "snake_x": 42392,
    "snake_y": 41387,
    "total_foods": 737,
    "total_slithers": 2,
    "visible_enemies": 0,
    "visible_foods": 19
  }
}